elemeno_ai_sdk/__init__.py
elemeno_ai_sdk/logger.py
elemeno_ai_sdk/utils.py
elemeno_ai_sdk/connector/datasource.py
elemeno_ai_sdk/cos/__init__.py
elemeno_ai_sdk/cos/base_cos.py
elemeno_ai_sdk/cos/minio.py
elemeno_ai_sdk/cos/s3.py
elemeno_ai_sdk/cos/file_utils/__init__.py
elemeno_ai_sdk/cos/file_utils/elastic_to_cos.py
elemeno_ai_sdk/cos/file_utils/elastic_to_cos_dask.py
elemeno_ai_sdk/cos/file_utils/zip_utils.py
elemeno_ai_sdk/cos/types/__init__.py
elemeno_ai_sdk/cos/types/cos_object.py
elemeno_ai_sdk/ml/mlhub_client.py
elemeno_ai_sdk/ml/registry.py
elemeno_ai_sdk/ml/automl/client.py
elemeno_ai_sdk/ml/conversion/__init__.py
elemeno_ai_sdk/ml/conversion/converter.py
elemeno_ai_sdk/ml/conversion/converter_abc.py
elemeno_ai_sdk/ml/conversion/sklearn.py
elemeno_ai_sdk/ml/conversion/tensorflow.py
elemeno_ai_sdk/ml/conversion/tflite.py
elemeno_ai_sdk/ml/conversion/torch.py
elemeno_ai_sdk/ml/features/__init__.py
elemeno_ai_sdk/ml/features/feature_store.py
elemeno_ai_sdk/ml/features/feature_table.py
elemeno_ai_sdk/ml/features/schema.py
elemeno_ai_sdk/ml/features/utils.py
elemeno_ai_sdk/ml/genai/__init__.py
elemeno_ai_sdk/ml/genai/chat.py
elemeno_ai_sdk/ml/genai/client.py
elemeno_ai_sdk/ml/genai/services.py
elemeno_ai_sdk/ml/inference/__init__.py
elemeno_ai_sdk/ml/inference/client.py
elemeno_ai_sdk/ml/inference/inference_response.py
elemeno_ai_sdk/ml/inference/input_space.py
elemeno_ai_sdk-0.6.17.dist-info/AUTHORS.rst
elemeno_ai_sdk-0.6.17.dist-info/LICENSE
elemeno_ai_sdk-0.6.17.dist-info/LICENSE-3RDPARTY.txt
elemeno_ai_sdk-0.6.17.dist-info/METADATA
elemeno_ai_sdk-0.6.17.dist-info/WHEEL
elemeno_ai_sdk-0.6.17.dist-info/entry_points.txt
elemeno_ai_sdk-0.6.17.dist-info/top_level.txt
elemeno_ai_sdk-0.6.17.dist-info/RECORD
